bem/__init__.py
bem/bem.py
bem/format_dataset.py
bem/teq_planet.py
bem-0.1.6.data/data/published_output/exoplanet.eu_catalog_15April.csv
bem-0.1.6.data/data/published_output/lc_test_scores.dat
bem-0.1.6.data/data/published_output/lc_train_scores.dat
bem-0.1.6.data/data/published_output/lc_train_sizes.dat
bem-0.1.6.data/data/published_output/r2_0.84_2019-07-23_17:05.pkl
bem-0.1.6.data/data/published_output/rv_mass_true.dat
bem-0.1.6.data/data/published_output/rv_radius_Forecaster.dat
bem-0.1.6.data/data/published_output/rv_radius_RF.dat
bem-0.1.6.data/data/published_output/rv_temp_eq_true.dat
bem-0.1.6.data/data/published_output/solar_system_planets_catalog.csv
bem-0.1.6.data/data/published_output/solar_system_planets_with_errors_radius.csv
bem-0.1.6.data/data/published_output/test_mass_true.dat
bem-0.1.6.data/data/published_output/test_radius_Fc_errorbars.dat
bem-0.1.6.data/data/published_output/test_radius_Forecaster.dat
bem-0.1.6.data/data/published_output/test_radius_RF.dat
bem-0.1.6.data/data/published_output/test_radius_RF_errorbars.dat
bem-0.1.6.data/data/published_output/test_radius_true.dat
bem-0.1.6.data/data/published_output/vc_depth_test_scores.dat
bem-0.1.6.data/data/published_output/vc_depth_train_scores.dat
bem-0.1.6.data/data/published_output/vc_features_test_scores.dat
bem-0.1.6.data/data/published_output/vc_features_train_scores.dat
bem-0.1.6.data/data/published_output/vc_tree_test_scores.dat
bem-0.1.6.data/data/published_output/vc_tree_train_scores.dat
bem-0.1.6.dist-info/LICENSE
bem-0.1.6.dist-info/METADATA
bem-0.1.6.dist-info/WHEEL
bem-0.1.6.dist-info/top_level.txt
bem-0.1.6.dist-info/RECORD
