Metadata-Version: 2.1
Name: bem
Version: 0.1.6
Summary: Random forest for exoplanets
Home-page: https://github.com/soleneulmer/bem
Author: Solène Ulmer-Moll
Author-email: solene.ulmer-moll@astro.up.pt
License: MIT
Platform: UNKNOWN
Requires-Dist: numpy
Requires-Dist: scipy
Requires-Dist: pandas
Requires-Dist: scikit-learn
Requires-Dist: matplotlib
Requires-Dist: astropy
Requires-Dist: lime
